com/__init__.py
com/lhw/__init__.py
com/lhw/bubble/__init__.py
com/lhw/bubble/richer.py
GiveMeARichNumber2-0.0.1.dist-info/LICENSE
GiveMeARichNumber2-0.0.1.dist-info/METADATA
GiveMeARichNumber2-0.0.1.dist-info/WHEEL
GiveMeARichNumber2-0.0.1.dist-info/entry_points.txt
GiveMeARichNumber2-0.0.1.dist-info/top_level.txt
GiveMeARichNumber2-0.0.1.dist-info/RECORD
