Metadata-Version: 2.1
Name: GiveMeARichNumber2
Version: 0.0.1
Summary: luckyNumber 36+2
Home-page: 
Author: jojo
License-File: LICENSE
Requires-Dist: requests >=2.25.1
Requires-Dist: beautifulsoup4 >=4.9.3
Requires-Dist: selenium >=3.141.0
Requires-Dist: lxml >=4.6.3
